fyerstest/__init__.py
fyerstest/data_ws.py
fyerstest/defines.py
fyerstest/fyers_api.py
fyerstest/fyers_logger.py
fyerstest/map.json
fyerstest/order_ws.py
fyerstest-0.6.dist-info/LICENSE.txt
fyerstest-0.6.dist-info/METADATA
fyerstest-0.6.dist-info/WHEEL
fyerstest-0.6.dist-info/top_level.txt
fyerstest-0.6.dist-info/RECORD
